ftl_desired_state/__init__.py
ftl_desired_state/ftl_desired_state.py
ftl_desired_state-0.0.1.dist-info/AUTHORS.rst
ftl_desired_state-0.0.1.dist-info/LICENSE
ftl_desired_state-0.0.1.dist-info/METADATA
ftl_desired_state-0.0.1.dist-info/WHEEL
ftl_desired_state-0.0.1.dist-info/top_level.txt
ftl_desired_state-0.0.1.dist-info/RECORD
