Metadata-Version: 2.1
Name: ftl-desired-state
Version: 0.0.1
Summary: A desired state reconciliation loop.
Home-page: https://github.com/benthomasson/ftl_desired_state
Author: Ben Thomasson
Author-email: ben.thomasson@gmail.com
License: Apache Software License 2.0
Keywords: ftl_desired_state
Platform: UNKNOWN
Classifier: Development Status :: 2 - Pre-Alpha
Classifier: Intended Audience :: Developers
Classifier: License :: OSI Approved :: Apache Software License
Classifier: Natural Language :: English
Classifier: Programming Language :: Python :: 3
Classifier: Programming Language :: Python :: 3.6
Classifier: Programming Language :: Python :: 3.7
Classifier: Programming Language :: Python :: 3.8
Requires-Python: >=3.6
